Workbook

Sheet README
A1: Electric Truck TCO & Fleet Economics Analysis
A2: Purpose | B2: Illustrative business-case model comparing diesel and battery-electric heavy freight trucks.
A3: Important | B3: This is an analytical portfolio project, not a commercial quote or investment recommendation.
A4: How to use | B4: Change yellow cells on the Inputs sheet; all calculations update in Excel.
A5: Scope | B5: 5-year TCO, ₹/km, ₹/ton-km, annual savings, simple payback, ROI proxy, and fleet scenarios for 10/100/1,000 trucks.
A6: Key limitation | B6: EV purchase price, maintenance, payload, utilization and other operating assumptions are scenario inputs and must be validated for a real fleet.

Sheet Inputs
A1: Input | B1: Value | C1: Unit | D1: Type / Source note
A2: Analysis date | B2: 2026-10-04 | D2: Scenario / project input.
A3: Annual distance per truck (km) | B3: 80000 | C3: km/year | D3: Scenario / project input.
A4: Analysis period (years) | B4: 5 | C4: years | D4: Scenario / project input.
A5: Diesel price (₹/L) | B5: 105.61 | C5: ₹/L | D5: Market reference: Vijayawada diesel price reported 3 Oct 2026; verify current rate before use.
A6: Diesel efficiency (km/L) | B6: 2.75 | C6: km/L | D6: Scenario input: midpoint of 2.25–3.25 km/L range reported for Tata Prima 5530.S by TrucksBuses.
A7: EV grid energy price (₹/kWh) | B7: 8.27 | C7: ₹/kWh | D7: Reference value from APERC tariff material; actual charging tariff/demand charges depend on connection and charging setup.
A8: EV battery nominal capacity (kWh) | B8: 450 | C8: kWh | D8: Tata Prima E.55S published 450 kWh option.
A9: EV advertised range (km) | B9: 350 | C9: km | D9: Tata Prima E.55S published range up to 350 km; real-world duty cycle may differ.
A10: Charging loss / overhead (%) | B10: 15 | C10: % | D10: Scenario assumption; replace with measured charger-to-battery/vehicle data.
A11: Diesel truck acquisition cost (₹) | B11: 4049000 | C11: ₹ | D11: Indicative ex-showroom market listing for Tata Prima 5530.S; validate with OEM/dealer.
A12: EV truck acquisition cost (₹) | B12: 6500000 | C12: ₹ | D12: Illustrative scenario assumption because public list price was not found in the reviewed source set.
A13: Diesel maintenance (₹/km) | B13: 10 | C13: ₹/km | D13: Illustrative scenario assumption; replace with fleet maintenance records.
A14: EV maintenance (₹/km) | B14: 6 | C14: ₹/km | D14: Illustrative scenario assumption; replace with fleet/OEM data.
... A19: Residual value (% of acquisition) | B19: 10 | C19: % | D19: Illustrative scenario assumption.

Sheet Unit Economics
A1: Metric | B1: Diesel | C1: Electric | D1: Formula / note
A2: Energy/fuel cost per km | B2: =Inputs!B5/Inputs!B6 | C2: =Inputs!B7*(Inputs!B8/Inputs!B9)*(1+Inputs!B10/100) | D2: Diesel: price/efficiency. EV: electricity × battery/range × charging overhead
A3: Maintenance cost per km | B3: =Inputs!B13 | C3: =Inputs!B14 | D3: Input assumption
A4: Other OPEX per km | B4: =Inputs!B15 | C4: =Inputs!B16 | D4: Input assumption
A5: Total operating cost per km | B5: =SUM(B2:B4) | C5: =SUM(C2:C4) | D5: Energy + maintenance + other OPEX
A6: ₹/ton-km | B6: =B5/Inputs!B17 | C6: =C5/Inputs!B17 | D6: Operating cost per km ÷ payload
A7: Annual distance (km) | B7: =Inputs!B3 | C7: =Inputs!B3 | D7: Input
A8: Annual operating cost | B8: =B5*B7 | C8: =C5*C7 | D8: Operating cost/km × annual distance
A9: Acquisition cost | B9: =Inputs!B11 | C9: =Inputs!B12 | D9: Truck purchase assumption
A10: Charging infrastructure CAPEX | B10: =0 | C10: =Inputs!B18 | D10: Applied to EV
A11: Initial investment | B11: =B9+B10 | C11: =C9+C10 | D11: Acquisition + charging infrastructure
A12: Residual value at end of period | B12: =B9*Inputs!B19/100 | C12: =C9*Inputs!B19/100 | D12: Residual % × acquisition
A13: 5-year operating cost | B13: =B8*Inputs!B4 | C13: =C8*Inputs!B4 | D13: Annual operating cost × years
A14: 5-year TCO before residual | B14: =B11+B13 | C14: =C11+C13 | D14: Initial investment + operating cost
A15: 5-year net TCO after residual | B15: =B14-B12 | C15: =C14-C12 | D15: TCO less residual value
A16: Annual operating savings vs diesel | B16: =0 | C16: =B8-C8 | D16: Diesel annual OPEX − EV annual OPEX
A17: Simple payback (years) | B17: =NA() | C17: =(C11-B11)/C16 | D17: Incremental initial investment ÷ annual operating savings
A18: 5-year ROI proxy | B18: =NA() | C18: =((C16*Inputs!B4)-(C11-B11))/(C11-B11) | D18: Cumulative operating savings less incremental investment, divided by incremental investment

Sheet Fleet Scenarios
A1: Fleet size | B1: Diesel initial investment | C1: EV initial investment | D1: Diesel annual OPEX | E1: EV annual OPEX | F1: Annual OPEX savings | G1: Incremental EV investment | H1: Simple payback (years) | I1: 5-year net TCO diesel | J1: 5-year net TCO EV
A2: 10 | B2: =Unit Economics!B11*A2 | C2: =Unit Economics!C11*A2 | D2: =Unit Economics!B8*A2 | E2: =Unit Economics!C8*A2 | F2: =D2-E2 | G2: =C2-B2 | H2: =G2/F2 | I2: =Unit Economics!B15*A2 | J2: =Unit Economics!C15*A2
A3: 100 | B3: =Unit Economics!B11*A3 | C3: =Unit Economics!C11*A3 | D3: =Unit Economics!B8*A3 | E3: =Unit Economics!C8*A3 | F3: =D3-E3 | G3: =C3-B3 | H3: =G3/F3 | I3: =Unit Economics!B15*A3 | J3: =Unit Economics!C15*A3
A4: 1000 | B4: =Unit Economics!B11*A4 | C4: =Unit Economics!C11*A4 | D4: =Unit Economics!B8*A4 | E4: =Unit Economics!C8*A4 | F4: =D4-E4 | G4: =C4-B4 | H4: =G4/F4 | I4: =Unit Economics!B15*A4 | J4: =Unit Economics!C15*A4

Sheet Sensitivity
A1: Electricity price (₹/kWh) | B1: EV energy cost/km | C1: EV total operating cost/km | D1: Annual OPEX savings/truck | E1: Payback years
A2: 6 | B2: =A2*(Inputs!B8/Inputs!B9)*(1+Inputs!B10/100) | C2: =B2+Inputs!B14+Inputs!B16 | D2: =Unit Economics!B8-C2*Inputs!B3 | E2: =(Unit Economics!C11-Unit Economics!B11)/D2
A3: 7 | B3: =A3*(Inputs!B8/Inputs!B9)*(1+Inputs!B10/100) | C3: =B3+Inputs!B14+Inputs!B16 | D3: =Unit Economics!B8-C3*Inputs!B3 | E3: =(Unit Economics!C11-Unit Economics!B11)/D3
A4: 8 | B4: =A4*(Inputs!B8/Inputs!B9)*(1+Inputs!B10/100) | C4: =B4+Inputs!B14+Inputs!B16 | D4: =Unit Economics!B8-C4*Inputs!B3 | E4: =(Unit Economics!C11-Unit Economics!B11)/D4
A5: 8.27 | B5: =A5*(Inputs!B8/Inputs!B9)*(1+Inputs!B10/100) | C5: =B5+Inputs!B14+Inputs!B16 | D5: =Unit Economics!B8-C5*Inputs!B3 | E5: =(Unit Economics!C11-Unit Economics!B11)/D5
A6: 9 | B6: =A6*(Inputs!B8/Inputs!B9)*(1+Inputs!B10/100) | C6: =B6+Inputs!B14+Inputs!B16 | D6: =Unit Economics!B8-C6*Inputs!B3 | E6: =(Unit Economics!C11-Unit Economics!B11)/D6
A7: 10 | B7: =A7*(Inputs!B8/Inputs!B9)*(1+Inputs!B10/100) | C7: =B7+Inputs!B14+Inputs!B16 | D7: =Unit Economics!B8-C7*Inputs!B3 | E7: =(Unit Economics!C11-Unit Economics!B11)/D7
A8: 11 | B8: =A8*(Inputs!B8/Inputs!B9)*(1+Inputs!B10/100) | C8: =B8+Inputs!B14+Inputs!B16 | D8: =Unit Economics!B8-C8*Inputs!B3 | E8: =(Unit Economics!C11-Unit Economics!B11)/D8

Sheet Sources
A1: Source | B1: What it supports | C1: URL
A2: Tata Motors – Prima E.55S | B2: 450 kWh battery option; up to 350 km range; 55,000 kg GVW; electric freight applications. | C2: https://trucks.tatamotors.com/product/tata-prima-e55s
A3: Tata Motors – Prima E.55S press release (10 Apr 2026) | B3: First batch delivered to BillionE Mobility; 250 additional order; deployment on key freight corridors; 450 kWh and up to 350 km. | C3: https://trucks.tatamotors.com/news/tata-motors-delivers-first-batch-of-electric-prima-E.55S-to-Billion-e-mobility-advances-zero-emission-freight-transport
A4: Tata Motors – Prima 5530.S | B4: 55,000 kg GCW, diesel configuration and specifications. | C4: https://trucks.tatamotors.com/prima/tata-prima-5530
A5: CSE – Zero Emission Trucks policy brief | B5: Comparative heavy-duty truck energy-consumption context; includes 55,000 kg tractor-trailer diesel benchmark of 1.9 km/L and 1.22 kWh/km BET equivalent. | C5: https://www.cseindia.org/content/downloadreports/12061
A6: APERC – FY2026-27 tariff press note | B6: States no tariff increase for any consumer category in FY2026-27; actual charging tariff still depends on connection/category and applicable charges. | C6: https://www.aperc.gov.in/admin/upload/PressNoteRSTFY202627English.pdf
A7: APERC – tariff/wheeling material | B7: Reference tariff/wheeling information; charging model should be validated for the actual connection and demand charges. | C7: https://aperc.gov.in/page/Tariff_Orders
A8: IndianOil – Petrol/Diesel price page | B8: Official source for checking current retail fuel prices; price can vary by outlet. | C8: https://iocl.com/petrol-diesel-price
A9: Vijayawada diesel price reference | B9: ₹105.61/L on 3 Oct 2026 as reported by Upstox; use as a dated market reference, not a fixed price. | C9: https://upstox.com/diesel-price/diesel-price-in-vijayawada/
A10: Tata Prima 5530.S market listing | B10: Indicative ex-showroom price around ₹40.49 lakh; third-party market listing, so validate with dealer/OEM. | C10: https://www.cmv360.com/trucks/tata/prima-5530s-bs6
